{"RootStyle": "-1693955950", "grimeSwatch": 1193919178, "name": "Scorpion Horvath", "emissiveAmount": 0.0, "swatches": [{"emissiveAmount": 0.0, "scratchRoughness": 1.0, "scratchBrightness": 0.0, "ior": 0.04, "colorVariant": {"name": "", "gradient_top_color": {"R_value": 0, "G_value": 0, "B_value": 0}, "gradient_mid_color": {"R_value": 0, "G_value": 0, "B_value": 0}, "gradient_bottom_color": {"R_value": 0, "G_value": 0, "B_value": 0}, "notes": "", "groupName": ""}, "normalPath": 813, "normalTextureTransform": {"X": 1.0, "Y": 1.0}, "color_and_roughness_texture_transform": {"X": 1.0, "Y": 1.0}, "scratchAlbedoTint": 0.0, "scratchColor": {"R_value": 0.0, "G_value": 0.0, "B_value": 0.0}, "metallic": 0.0, "scratchMetallic": 0.0, "roughnessBlack": 0.0, "scratchIor": 0.04, "roughnessWhite": 1.0, "roughness": 4, "groupName": "", "emissiveIntensity": 0.0, "colorGradientMap": 7443, "swatchId": 0, "swatchref": 1640353198}, {"emissiveAmount": 0.0, "scratchRoughness": 0.5, "scratchBrightness": 0.0, "ior": 0.04, "colorVariant": {"name": 1035900783, "gradient_top_color": {"R_value": 0.9706813, "G_value": 0.3177795, "B_value": 0.0174221}, "gradient_mid_color": {"R_value": 0.8419, "G_value": 0.3349, "B_value": 0.0169}, "gradient_bottom_color": {"R_value": 0.7236829, "G_value": 0.2620358, "B_value": 0.01881802}, "notes": "", "groupName": ""}, "normalPath": 2008263443, "normalTextureTransform": {"X": 5.0, "Y": 5.0}, "color_and_roughness_texture_transform": {"X": 5.0, "Y": 5.0}, "scratchAlbedoTint": 0.0, "scratchColor": {"R_value": 0.3185469, "G_value": 0.3185469, "B_value": 0.3185469}, "metallic": 1.0, "scratchMetallic": 1.0, "roughnessBlack": 0.06, "scratchIor": 0.04, "roughnessWhite": 0.07, "roughness": 4, "groupName": "smooth", "emissiveIntensity": 0.0, "colorGradientMap": -1250454321, "swatchId": -653723740, "swatchref": -551660791}, {"emissiveAmount": 0.0, "scratchRoughness": 0.65, "scratchBrightness": 0.0, "ior": 0.02, "colorVariant": {"name": -16744166, "gradient_top_color": {"R_value": 0.5209957, "G_value": 0.3967554, "B_value": 0.184475}, "gradient_mid_color": {"R_value": 0.4255405, "G_value": 0.3246599, "B_value": 0.1519247}, "gradient_bottom_color": {"R_value": 0.4255405, "G_value": 0.3246599, "B_value": 0.1519247}, "notes": "Scorpion Horvath", "groupName": ""}, "normalPath": 715266683, "normalTextureTransform": {"X": 1.0, "Y": 1.0}, "color_and_roughness_texture_transform": {"X": 0.25, "Y": 0.25}, "scratchAlbedoTint": 0.0, "scratchColor": {"R_value": 0.3005438, "G_value": 0.3005438, "B_value": 0.3005438}, "metallic": 0.0, "scratchMetallic": 1.0, "roughnessBlack": 0.29, "scratchIor": 0.04, "roughnessWhite": 0.52, "roughness": 4, "groupName": "", "emissiveIntensity": 0.0, "colorGradientMap": 1338683167, "swatchId": 299523653, "swatchref": -1803579619}, {"emissiveAmount": 0.0, "scratchRoughness": 0.8, "scratchBrightness": 0.0, "ior": 0.04, "colorVariant": {"name": -943546839, "gradient_top_color": {"R_value": 0.121264, "G_value": 0.09341104, "B_value": 0.06336238}, "gradient_mid_color": {"R_value": 0.121264, "G_value": 0.09341104, "B_value": 0.06336238}, "gradient_bottom_color": {"R_value": 0.121264, "G_value": 0.09341104, "B_value": 0.06336238}, "notes": "Scorpion Horvath", "groupName": ""}, "normalPath": -6187303, "normalTextureTransform": {"X": 1.0, "Y": 1.0}, "color_and_roughness_texture_transform": {"X": 1.0, "Y": 1.0}, "scratchAlbedoTint": 0.0, "scratchColor": {"R_value": 0.1328683, "G_value": 0.1328683, "B_value": 0.1328683}, "metallic": 0.0, "scratchMetallic": 0.0, "roughnessBlack": 0.55, "scratchIor": 0.04, "roughnessWhite": 0.71, "roughness": 4, "groupName": "7FB906D7", "emissiveIntensity": 0.0, "colorGradientMap": 1993185360, "swatchId": 1062531877, "swatchref": 249403399}, {"emissiveAmount": 0.0, "scratchRoughness": 0.65, "scratchBrightness": 0.0, "ior": 0.02, "colorVariant": {"name": 243166993, "gradient_top_color": {"R_value": 0.174728, "G_value": 0.1237718, "B_value": 0.05565481}, "gradient_mid_color": {"R_value": 0.1518247, "G_value": 0.1110378, "B_value": 0.05473497}, "gradient_bottom_color": {"R_value": 0.15564, "G_value": 0.1129031, "B_value": 0.0543872}, "notes": "Scorpion Horvath", "groupName": ""}, "normalPath": 715266683, "normalTextureTransform": {"X": 1.0, "Y": 1.0}, "color_and_roughness_texture_transform": {"X": 0.25, "Y": 0.25}, "scratchAlbedoTint": 0.0, "scratchColor": {"R_value": 0.3005438, "G_value": 0.3005438, "B_value": 0.3005438}, "metallic": 0.0, "scratchMetallic": 1.0, "roughnessBlack": 0.29, "scratchIor": 0.04, "roughnessWhite": 0.52, "roughness": 5.0, "groupName": "", "emissiveIntensity": 0.0, "colorGradientMap": 1338683167, "swatchId": -1867646230, "swatchref": -1803579619}, {"emissiveAmount": 0.0, "scratchRoughness": 0.65, "scratchBrightness": 0.0, "ior": 0.02, "colorVariant": {"name": -1255704640, "gradient_top_color": {"R_value": 0.1274377, "G_value": 0.1119324, "B_value": 0.07036012}, "gradient_mid_color": {"R_value": 0.1274377, "G_value": 0.1119324, "B_value": 0.07036012}, "gradient_bottom_color": {"R_value": 0.1274377, "G_value": 0.1119324, "B_value": 0.07036012}, "notes": "Scorpion Horvath", "groupName": ""}, "normalPath": 715266683, "normalTextureTransform": {"X": 1.0, "Y": 1.0}, "color_and_roughness_texture_transform": {"X": 0.25, "Y": 0.25}, "scratchAlbedoTint": 0.0, "scratchColor": {"R_value": 0.3005438, "G_value": 0.3005438, "B_value": 0.3005438}, "metallic": 0.0, "scratchMetallic": 1.0, "roughnessBlack": 0.29, "scratchIor": 0.04, "roughnessWhite": 0.52, "roughness": 4, "groupName": "", "emissiveIntensity": 0.0, "colorGradientMap": 1338683167, "swatchId": -860651894, "swatchref": -1803579619}, {"emissiveAmount": 0.0, "scratchRoughness": 1.0, "scratchBrightness": 0.0, "ior": 0.04, "colorVariant": {"name": -1367564405, "gradient_top_color": {"R_value": 0.002941395, "G_value": 0.002941395, "B_value": 0.002941395}, "gradient_mid_color": {"R_value": 0.005642331, "G_value": 0.005642331, "B_value": 0.005642331}, "gradient_bottom_color": {"R_value": 0.007322987, "G_value": 0.007322987, "B_value": 0.007322987}, "notes": "", "groupName": ""}, "normalPath": 470118482, "normalTextureTransform": {"X": 1.0, "Y": 1.0}, "color_and_roughness_texture_transform": {"X": 1.0, "Y": 1.0}, "scratchAlbedoTint": 0.0, "scratchColor": {"R_value": 0.0, "G_value": 0.0, "B_value": 0.0}, "metallic": 0.0, "scratchMetallic": 0.0, "roughnessBlack": 0.309, "scratchIor": 0.04, "roughnessWhite": 0.647, "roughness": 4, "groupName": "grime", "emissiveIntensity": 0.0, "colorGradientMap": 1595717704, "swatchId": 1193919178, "swatchref": 516247910}, {"emissiveAmount": 1.0, "scratchRoughness": 0.7, "scratchBrightness": 0.0, "ior": 0.04, "colorVariant": {"name": 185608551, "gradient_top_color": {"R_value": 1.0, "G_value": 1.0, "B_value": 1.0}, "gradient_mid_color": {"R_value": 1.0, "G_value": 1.0, "B_value": 1.0}, "gradient_bottom_color": {"R_value": 1.0, "G_value": 1.0, "B_value": 1.0}, "notes": "white", "groupName": ""}, "normalPath": 1051336669, "normalTextureTransform": {"X": 1.0, "Y": 1.0}, "color_and_roughness_texture_transform": {"X": 1.0, "Y": 1.0}, "scratchAlbedoTint": 0.0, "scratchColor": {"R_value": 0.0399, "G_value": 0.0399, "B_value": 0.0399}, "metallic": 0.0, "scratchMetallic": 0.0, "roughnessBlack": 0.321, "scratchIor": 0.02, "roughnessWhite": 0.321, "roughness": 4, "groupName": "smooth", "emissiveIntensity": 2.0, "colorGradientMap": -1099619198, "swatchId": -1784602160, "swatchref": -369036884}, {"emissiveAmount": 0.0, "scratchRoughness": 0.85, "scratchBrightness": 0.0, "ior": 0.04, "colorVariant": {"name": 998781505, "gradient_top_color": {"R_value": 0.02638551, "G_value": 0.02522446, "B_value": 0.02412565}, "gradient_mid_color": {"R_value": 0.02777092, "G_value": 0.02570925, "B_value": 0.02489432}, "gradient_bottom_color": {"R_value": 0.02030235, "G_value": 0.01944769, "B_value": 0.01910501}, "notes": "", "groupName": ""}, "normalPath": -1619437289, "normalTextureTransform": {"X": 0.5, "Y": 0.5}, "color_and_roughness_texture_transform": {"X": 0.5, "Y": 0.5}, "scratchAlbedoTint": 0.0, "scratchColor": {"R_value": 0.1428923, "G_value": 0.1428923, "B_value": 0.1428923}, "metallic": 1.0, "scratchMetallic": 1.0, "roughnessBlack": 0.42, "scratchIor": 0.04, "roughnessWhite": 0.51, "roughness": 4, "groupName": "metal", "emissiveIntensity": 0.0, "colorGradientMap": 2010517745, "swatchId": -1777392143, "swatchref": -1568118955}, {"emissiveAmount": 0.0, "scratchRoughness": 0.65, "scratchBrightness": 0.0, "ior": 0.04, "colorVariant": {"name": -395469504, "gradient_top_color": {"R_value": 0.6523788, "G_value": 0.5163577, "B_value": 0.2735479}, "gradient_mid_color": {"R_value": 0.5623174, "G_value": 0.3849363, "B_value": 0.118099}, "gradient_bottom_color": {"R_value": 0.4338795, "G_value": 0.2948259, "B_value": 0.1521431}, "notes": "Scorpion Horvath", "groupName": ""}, "normalPath": -1585344723, "normalTextureTransform": {"X": 0.5, "Y": 0.5}, "color_and_roughness_texture_transform": {"X": 0.5, "Y": 0.5}, "scratchAlbedoTint": 0.0, "scratchColor": {"R_value": 0.3005438, "G_value": 0.3005438, "B_value": 0.3005438}, "metallic": 0.0, "scratchMetallic": 1.0, "roughnessBlack": 0.39, "scratchIor": 0.04, "roughnessWhite": 0.51, "roughness": 4, "groupName": "", "emissiveIntensity": 0.0, "colorGradientMap": 718607112, "swatchId": 2008159925, "swatchref": 12828223}, {"emissiveAmount": 0.0, "scratchRoughness": 0.9, "scratchBrightness": 0.0, "ior": 0.04, "colorVariant": {"name": 13415457, "gradient_top_color": {"R_value": 0.4851501, "G_value": 0.2788943, "B_value": 0.1328683}, "gradient_mid_color": {"R_value": 0.3104375, "G_value": 0.1800982, "B_value": 0.08718561}, "gradient_bottom_color": {"R_value": 0.4851501, "G_value": 0.2788943, "B_value": 0.1328683}, "notes": "83B76E77", "groupName": ""}, "normalPath": -192696709, "normalTextureTransform": {"X": 1.0, "Y": 1.0}, "color_and_roughness_texture_transform": {"X": 1.0, "Y": 1.0}, "scratchAlbedoTint": 0.0, "scratchColor": {"R_value": 0.3339317, "G_value": 0.3339317, "B_value": 0.3339317}, "metallic": 1.0, "scratchMetallic": 1.0, "roughnessBlack": 0.176, "scratchIor": 0.04, "roughnessWhite": 0.5, "roughness": 8.0, "groupName": "527A6693", "emissiveIntensity": 0.0, "colorGradientMap": -602448329, "swatchId": 2029379834, "swatchref": 1653549194}, {"emissiveAmount": 0.0, "scratchRoughness": 0.65, "scratchBrightness": 0.0, "ior": 0.02, "colorVariant": {"name": -291565808, "gradient_top_color": {"R_value": 0.4667251, "G_value": 0.2716701, "B_value": 0.1379153}, "gradient_mid_color": {"R_value": 0.3997534, "G_value": 0.2525906, "B_value": 0.1431081}, "gradient_bottom_color": {"R_value": 0.4874054, "G_value": 0.2779045, "B_value": 0.1332731}, "notes": "Scorpion Horvath", "groupName": ""}, "normalPath": 715266683, "normalTextureTransform": {"X": 1.0, "Y": 1.0}, "color_and_roughness_texture_transform": {"X": 0.25, "Y": 0.25}, "scratchAlbedoTint": 0.0, "scratchColor": {"R_value": 0.3005438, "G_value": 0.3005438, "B_value": 0.3005438}, "metallic": 0.0, "scratchMetallic": 1.0, "roughnessBlack": 0.29, "scratchIor": 0.04, "roughnessWhite": 0.52, "roughness": 3.0, "groupName": "", "emissiveIntensity": 0.0, "colorGradientMap": 1338683167, "swatchId": -935078309, "swatchref": -1803579619}, {"emissiveAmount": 0.0, "scratchRoughness": 0.8, "scratchBrightness": 0.0, "ior": 0.04, "colorVariant": {"name": 1335817985, "gradient_top_color": {"R_value": 0.121264, "G_value": 0.09341104, "B_value": 0.06336238}, "gradient_mid_color": {"R_value": 0.121264, "G_value": 0.09341104, "B_value": 0.06336238}, "gradient_bottom_color": {"R_value": 0.121264, "G_value": 0.09341104, "B_value": 0.06336238}, "notes": "Splinter Desert", "groupName": ""}, "normalPath": 478054507, "normalTextureTransform": {"X": 0.5, "Y": 0.5}, "color_and_roughness_texture_transform": {"X": 0.5, "Y": 0.5}, "scratchAlbedoTint": 0.0, "scratchColor": {"R_value": 0.1328683, "G_value": 0.1328683, "B_value": 0.1328683}, "metallic": 0.0, "scratchMetallic": 0.0, "roughnessBlack": 0.309, "scratchIor": 0.04, "roughnessWhite": 0.4, "roughness": 5.0, "groupName": "7FB906D7", "emissiveIntensity": 0.0, "colorGradientMap": -1284203363, "swatchId": -1251036865, "swatchref": 517024975}], "grimeAmount": 1.0, "regionLayers": {"-2064803309": {"layers": [{"colorBlend": true, "swatch": 2008159925, "ignoreTexelDensity": false, "normalBlend": false}, {"colorBlend": true, "swatch": -935078309, "ignoreTexelDensity": false, "normalBlend": false}, {"colorBlend": true, "swatch": -1867646230, "ignoreTexelDensity": false, "normalBlend": false}, {"colorBlend": true, "swatch": 299523653, "ignoreTexelDensity": false, "normalBlend": false}, {"colorBlend": true, "swatch": -860651894, "ignoreTexelDensity": false, "normalBlend": false}, {"colorBlend": true, "swatch": 2008159925, "ignoreTexelDensity": false, "normalBlend": false}, {"colorBlend": true, "swatch": 1193919178, "ignoreTexelDensity": false, "normalBlend": false}], "material": 6, "bodyPart": "r_shin"}, "-746683297": {"layers": [{"colorBlend": true, "swatch": 2008159925, "ignoreTexelDensity": false, "normalBlend": false}, {"colorBlend": true, "swatch": -860651894, "ignoreTexelDensity": false, "normalBlend": false}, {"colorBlend": true, "swatch": 2008159925, "ignoreTexelDensity": false, "normalBlend": false}, {"colorBlend": true, "swatch": -860651894, "ignoreTexelDensity": false, "normalBlend": false}, {"colorBlend": true, "swatch": -1777392143, "ignoreTexelDensity": false, "normalBlend": false}, {"colorBlend": true, "swatch": 1062531877, "ignoreTexelDensity": false, "normalBlend": false}, {"colorBlend": true, "swatch": 1193919178, "ignoreTexelDensity": false, "normalBlend": false}], "material": 6, "bodyPart": "helmet"}, "937533364": {"layers": [{"colorBlend": true, "swatch": 2008159925, "ignoreTexelDensity": false, "normalBlend": false}, {"colorBlend": true, "swatch": 2008159925, "ignoreTexelDensity": false, "normalBlend": false}, {"colorBlend": true, "swatch": 2008159925, "ignoreTexelDensity": false, "normalBlend": false}, {"colorBlend": true, "swatch": -935078309, "ignoreTexelDensity": false, "normalBlend": false}, {"colorBlend": true, "swatch": 299523653, "ignoreTexelDensity": false, "normalBlend": false}, {"colorBlend": true, "swatch": 2008159925, "ignoreTexelDensity": false, "normalBlend": false}, {"colorBlend": true, "swatch": 1193919178, "ignoreTexelDensity": false, "normalBlend": false}], "material": 6, "bodyPart": "l_thigh"}, "252394811": {"layers": [{"colorBlend": true, "swatch": 2008159925, "ignoreTexelDensity": false, "normalBlend": false}, {"colorBlend": true, "swatch": 2008159925, "ignoreTexelDensity": false, "normalBlend": false}, {"colorBlend": true, "swatch": 2008159925, "ignoreTexelDensity": false, "normalBlend": false}, {"colorBlend": true, "swatch": -935078309, "ignoreTexelDensity": false, "normalBlend": false}, {"colorBlend": true, "swatch": 299523653, "ignoreTexelDensity": false, "normalBlend": false}, {"colorBlend": true, "swatch": 2008159925, "ignoreTexelDensity": false, "normalBlend": false}, {"colorBlend": true, "swatch": 1193919178, "ignoreTexelDensity": false, "normalBlend": false}], "material": 6, "bodyPart": "r_thigh"}, "1138711306": {"layers": [{"colorBlend": true, "swatch": 2008159925, "ignoreTexelDensity": false, "normalBlend": false}, {"colorBlend": true, "swatch": -935078309, "ignoreTexelDensity": false, "normalBlend": false}, {"colorBlend": true, "swatch": 2008159925, "ignoreTexelDensity": false, "normalBlend": false}, {"colorBlend": true, "swatch": -1867646230, "ignoreTexelDensity": false, "normalBlend": false}, {"colorBlend": true, "swatch": 299523653, "ignoreTexelDensity": false, "normalBlend": false}, {"colorBlend": true, "swatch": -1784602160, "ignoreTexelDensity": false, "normalBlend": false}, {"colorBlend": true, "swatch": 1193919178, "ignoreTexelDensity": false, "normalBlend": false}], "material": 6, "bodyPart": "torso_belt"}, "-2145792588": {"layers": [{"colorBlend": true, "swatch": 2008159925, "ignoreTexelDensity": false, "normalBlend": false}, {"colorBlend": true, "swatch": -935078309, "ignoreTexelDensity": false, "normalBlend": false}, {"colorBlend": true, "swatch": -1251036865, "ignoreTexelDensity": false, "normalBlend": false}, {"colorBlend": true, "swatch": -1251036865, "ignoreTexelDensity": false, "normalBlend": false}, {"colorBlend": true, "swatch": -935078309, "ignoreTexelDensity": false, "normalBlend": false}, {"colorBlend": true, "swatch": -1784602160, "ignoreTexelDensity": false, "normalBlend": false}, {"colorBlend": true, "swatch": 1193919178, "ignoreTexelDensity": false, "normalBlend": false}], "material": 6, "bodyPart": "torso"}, "-1908503075": {"layers": [{"colorBlend": true, "swatch": 299523653, "ignoreTexelDensity": false, "normalBlend": false}, {"colorBlend": true, "swatch": 299523653, "ignoreTexelDensity": false, "normalBlend": false}, {"colorBlend": true, "swatch": 1062531877, "ignoreTexelDensity": false, "normalBlend": false}, {"colorBlend": true, "swatch": 1193919178, "ignoreTexelDensity": false, "normalBlend": false}], "material": 7, "bodyPart": "l_kneepad"}, "927567337": {"layers": [{"colorBlend": true, "swatch": 299523653, "ignoreTexelDensity": false, "normalBlend": false}, {"colorBlend": true, "swatch": 299523653, "ignoreTexelDensity": false, "normalBlend": false}, {"colorBlend": true, "swatch": 1062531877, "ignoreTexelDensity": false, "normalBlend": false}, {"colorBlend": true, "swatch": 1193919178, "ignoreTexelDensity": false, "normalBlend": false}], "material": 7, "bodyPart": "r_kneepad"}, "-592012529": {"layers": [{"colorBlend": true, "swatch": 299523653, "ignoreTexelDensity": false, "normalBlend": false}, {"colorBlend": true, "swatch": -935078309, "ignoreTexelDensity": false, "normalBlend": false}, {"colorBlend": true, "swatch": 1062531877, "ignoreTexelDensity": false, "normalBlend": false}, {"colorBlend": true, "swatch": -1251036865, "ignoreTexelDensity": false, "normalBlend": false}, {"colorBlend": true, "swatch": -935078309, "ignoreTexelDensity": false, "normalBlend": false}, {"colorBlend": true, "swatch": 0, "ignoreTexelDensity": false, "normalBlend": false}, {"colorBlend": true, "swatch": 1193919178, "ignoreTexelDensity": false, "normalBlend": false}], "material": 6, "bodyPart": "l_armup"}, "1733594109": {"layers": [{"colorBlend": true, "swatch": 299523653, "ignoreTexelDensity": false, "normalBlend": false}, {"colorBlend": true, "swatch": -935078309, "ignoreTexelDensity": false, "normalBlend": false}, {"colorBlend": true, "swatch": 1062531877, "ignoreTexelDensity": false, "normalBlend": false}, {"colorBlend": true, "swatch": -1251036865, "ignoreTexelDensity": false, "normalBlend": false}, {"colorBlend": true, "swatch": -935078309, "ignoreTexelDensity": false, "normalBlend": false}, {"colorBlend": true, "swatch": 0, "ignoreTexelDensity": false, "normalBlend": false}, {"colorBlend": true, "swatch": 1193919178, "ignoreTexelDensity": false, "normalBlend": false}], "material": 6, "bodyPart": "r_armup"}, "1066512234": {"layers": [{"colorBlend": true, "swatch": 2008159925, "ignoreTexelDensity": false, "normalBlend": false}, {"colorBlend": true, "swatch": -1867646230, "ignoreTexelDensity": false, "normalBlend": false}, {"colorBlend": true, "swatch": 299523653, "ignoreTexelDensity": false, "normalBlend": false}, {"colorBlend": true, "swatch": -1867646230, "ignoreTexelDensity": false, "normalBlend": false}, {"colorBlend": true, "swatch": 299523653, "ignoreTexelDensity": false, "normalBlend": false}, {"colorBlend": true, "swatch": 1062531877, "ignoreTexelDensity": false, "normalBlend": false}, {"colorBlend": true, "swatch": 1193919178, "ignoreTexelDensity": false, "normalBlend": false}], "material": 6, "bodyPart": "l_armfor"}, "-1149815856": {"layers": [{"colorBlend": true, "swatch": 2008159925, "ignoreTexelDensity": false, "normalBlend": false}, {"colorBlend": true, "swatch": -1867646230, "ignoreTexelDensity": false, "normalBlend": false}, {"colorBlend": true, "swatch": 299523653, "ignoreTexelDensity": false, "normalBlend": false}, {"colorBlend": true, "swatch": -1867646230, "ignoreTexelDensity": false, "normalBlend": false}, {"colorBlend": true, "swatch": 299523653, "ignoreTexelDensity": false, "normalBlend": false}, {"colorBlend": true, "swatch": 1062531877, "ignoreTexelDensity": false, "normalBlend": false}, {"colorBlend": true, "swatch": 1193919178, "ignoreTexelDensity": false, "normalBlend": false}], "material": 6, "bodyPart": "r_armfor"}, "1420626520": {"layers": [{"colorBlend": true, "swatch": -653723740, "ignoreTexelDensity": false, "normalBlend": false}, {"colorBlend": true, "swatch": 0, "ignoreTexelDensity": false, "normalBlend": false}, {"colorBlend": true, "swatch": 0, "ignoreTexelDensity": false, "normalBlend": false}, {"colorBlend": true, "swatch": 0, "ignoreTexelDensity": false, "normalBlend": false}, {"colorBlend": true, "swatch": 0, "ignoreTexelDensity": false, "normalBlend": false}, {"colorBlend": true, "swatch": 0, "ignoreTexelDensity": false, "normalBlend": false}, {"colorBlend": true, "swatch": 0, "ignoreTexelDensity": false, "normalBlend": false}], "material": 0, "bodyPart": "mp_visor"}, "1574148266": {"layers": [{"colorBlend": true, "swatch": 1062531877, "ignoreTexelDensity": false, "normalBlend": false}, {"colorBlend": true, "swatch": 1062531877, "ignoreTexelDensity": false, "normalBlend": false}, {"colorBlend": true, "swatch": -1251036865, "ignoreTexelDensity": false, "normalBlend": false}, {"colorBlend": true, "swatch": 1193919178, "ignoreTexelDensity": false, "normalBlend": false}], "material": 7, "bodyPart": "neck"}, "1888796347": {"layers": [{"colorBlend": true, "swatch": 2008159925, "ignoreTexelDensity": false, "normalBlend": false}, {"colorBlend": true, "swatch": 2008159925, "ignoreTexelDensity": false, "normalBlend": false}, {"colorBlend": true, "swatch": -1867646230, "ignoreTexelDensity": false, "normalBlend": false}, {"colorBlend": true, "swatch": 299523653, "ignoreTexelDensity": false, "normalBlend": false}, {"colorBlend": true, "swatch": -935078309, "ignoreTexelDensity": false, "normalBlend": false}, {"colorBlend": true, "swatch": 0, "ignoreTexelDensity": false, "normalBlend": false}, {"colorBlend": true, "swatch": 1193919178, "ignoreTexelDensity": false, "normalBlend": false}], "material": 6, "bodyPart": "l_shoulderpad"}, "-1603936156": {"layers": [{"colorBlend": true, "swatch": 2008159925, "ignoreTexelDensity": false, "normalBlend": false}, {"colorBlend": true, "swatch": 2008159925, "ignoreTexelDensity": false, "normalBlend": false}, {"colorBlend": true, "swatch": -1867646230, "ignoreTexelDensity": false, "normalBlend": false}, {"colorBlend": true, "swatch": 299523653, "ignoreTexelDensity": false, "normalBlend": false}, {"colorBlend": true, "swatch": -935078309, "ignoreTexelDensity": false, "normalBlend": false}, {"colorBlend": true, "swatch": 0, "ignoreTexelDensity": false, "normalBlend": false}, {"colorBlend": true, "swatch": 1193919178, "ignoreTexelDensity": false, "normalBlend": false}], "material": 6, "bodyPart": "r_shoulderpad"}, "1644532521": {"layers": [{"colorBlend": true, "swatch": -1251036865, "ignoreTexelDensity": false, "normalBlend": false}, {"colorBlend": true, "swatch": -1251036865, "ignoreTexelDensity": false, "normalBlend": false}, {"colorBlend": true, "swatch": -1867646230, "ignoreTexelDensity": false, "normalBlend": false}, {"colorBlend": true, "swatch": 1062531877, "ignoreTexelDensity": false, "normalBlend": false}, {"colorBlend": true, "swatch": 2008159925, "ignoreTexelDensity": false, "normalBlend": false}, {"colorBlend": true, "swatch": 2008159925, "ignoreTexelDensity": false, "normalBlend": false}, {"colorBlend": true, "swatch": 1193919178, "ignoreTexelDensity": false, "normalBlend": false}], "material": 6, "bodyPart": "l_glove"}, "2088789481": {"layers": [{"colorBlend": true, "swatch": -1251036865, "ignoreTexelDensity": false, "normalBlend": false}, {"colorBlend": true, "swatch": -1251036865, "ignoreTexelDensity": false, "normalBlend": false}, {"colorBlend": true, "swatch": -1867646230, "ignoreTexelDensity": false, "normalBlend": false}, {"colorBlend": true, "swatch": 1062531877, "ignoreTexelDensity": false, "normalBlend": false}, {"colorBlend": true, "swatch": 2008159925, "ignoreTexelDensity": false, "normalBlend": false}, {"colorBlend": true, "swatch": 2008159925, "ignoreTexelDensity": false, "normalBlend": false}, {"colorBlend": true, "swatch": 1193919178, "ignoreTexelDensity": false, "normalBlend": false}], "material": 6, "bodyPart": "r_glove"}, "1742558826": {"layers": [{"colorBlend": true, "swatch": -1251036865, "ignoreTexelDensity": false, "normalBlend": false}, {"colorBlend": true, "swatch": 1062531877, "ignoreTexelDensity": false, "normalBlend": false}, {"colorBlend": true, "swatch": 299523653, "ignoreTexelDensity": false, "normalBlend": false}, {"colorBlend": true, "swatch": 1193919178, "ignoreTexelDensity": false, "normalBlend": false}], "material": 7, "bodyPart": "l_knee"}, "1473355996": {"layers": [{"colorBlend": true, "swatch": -1251036865, "ignoreTexelDensity": false, "normalBlend": false}, {"colorBlend": true, "swatch": 1062531877, "ignoreTexelDensity": false, "normalBlend": false}, {"colorBlend": true, "swatch": 299523653, "ignoreTexelDensity": false, "normalBlend": false}, {"colorBlend": true, "swatch": 1193919178, "ignoreTexelDensity": false, "normalBlend": false}], "material": 7, "bodyPart": "r_knee"}, "691694335": {"layers": [{"colorBlend": true, "swatch": 2008159925, "ignoreTexelDensity": false, "normalBlend": false}, {"colorBlend": true, "swatch": -935078309, "ignoreTexelDensity": false, "normalBlend": false}, {"colorBlend": true, "swatch": -1867646230, "ignoreTexelDensity": false, "normalBlend": false}, {"colorBlend": true, "swatch": 299523653, "ignoreTexelDensity": false, "normalBlend": false}, {"colorBlend": true, "swatch": -860651894, "ignoreTexelDensity": false, "normalBlend": false}, {"colorBlend": true, "swatch": 2008159925, "ignoreTexelDensity": false, "normalBlend": false}, {"colorBlend": true, "swatch": 1193919178, "ignoreTexelDensity": false, "normalBlend": false}], "material": 6, "bodyPart": "l_shin"}, "-1627968715": {"layers": [{"colorBlend": true, "swatch": 2008159925, "ignoreTexelDensity": false, "normalBlend": false}, {"colorBlend": true, "swatch": 2008159925, "ignoreTexelDensity": false, "normalBlend": false}, {"colorBlend": true, "swatch": 2008159925, "ignoreTexelDensity": false, "normalBlend": false}, {"colorBlend": true, "swatch": -1867646230, "ignoreTexelDensity": false, "normalBlend": false}, {"colorBlend": true, "swatch": -935078309, "ignoreTexelDensity": false, "normalBlend": false}, {"colorBlend": true, "swatch": -935078309, "ignoreTexelDensity": false, "normalBlend": false}, {"colorBlend": true, "swatch": 1193919178, "ignoreTexelDensity": false, "normalBlend": false}], "material": 6, "bodyPart": "l_boot"}, "-1273831941": {"layers": [{"colorBlend": true, "swatch": 2008159925, "ignoreTexelDensity": false, "normalBlend": false}, {"colorBlend": true, "swatch": 2008159925, "ignoreTexelDensity": false, "normalBlend": false}, {"colorBlend": true, "swatch": 2008159925, "ignoreTexelDensity": false, "normalBlend": false}, {"colorBlend": true, "swatch": -1867646230, "ignoreTexelDensity": false, "normalBlend": false}, {"colorBlend": true, "swatch": -935078309, "ignoreTexelDensity": false, "normalBlend": false}, {"colorBlend": true, "swatch": -935078309, "ignoreTexelDensity": false, "normalBlend": false}, {"colorBlend": true, "swatch": 1193919178, "ignoreTexelDensity": false, "normalBlend": false}], "material": 6, "bodyPart": "r_boot"}, "-825191764": {"layers": [{"colorBlend": true, "swatch": 2008159925, "ignoreTexelDensity": false, "normalBlend": false}, {"colorBlend": true, "swatch": 2029379834, "ignoreTexelDensity": false, "normalBlend": false}, {"colorBlend": true, "swatch": -1867646230, "ignoreTexelDensity": false, "normalBlend": false}, {"colorBlend": true, "swatch": 299523653, "ignoreTexelDensity": false, "normalBlend": false}, {"colorBlend": true, "swatch": 2008159925, "ignoreTexelDensity": false, "normalBlend": false}, {"colorBlend": true, "swatch": 0, "ignoreTexelDensity": false, "normalBlend": false}, {"colorBlend": true, "swatch": 1193919178, "ignoreTexelDensity": false, "normalBlend": false}], "material": 2, "bodyPart": "r_shoulderpad_legendary"}, "-687430240": {"layers": [{"colorBlend": true, "swatch": 2008159925, "ignoreTexelDensity": false, "normalBlend": false}, {"colorBlend": true, "swatch": 2029379834, "ignoreTexelDensity": false, "normalBlend": false}, {"colorBlend": true, "swatch": -1867646230, "ignoreTexelDensity": false, "normalBlend": false}, {"colorBlend": true, "swatch": 299523653, "ignoreTexelDensity": false, "normalBlend": false}, {"colorBlend": true, "swatch": 2008159925, "ignoreTexelDensity": false, "normalBlend": false}, {"colorBlend": true, "swatch": 0, "ignoreTexelDensity": false, "normalBlend": false}, {"colorBlend": true, "swatch": 1193919178, "ignoreTexelDensity": false, "normalBlend": false}], "material": 2, "bodyPart": "l_shoulderpad_legendary"}, "-1129113227": {"layers": [{"colorBlend": true, "swatch": -1251036865, "ignoreTexelDensity": false, "normalBlend": false}, {"colorBlend": true, "swatch": -1251036865, "ignoreTexelDensity": false, "normalBlend": false}, {"colorBlend": true, "swatch": -1867646230, "ignoreTexelDensity": false, "normalBlend": false}, {"colorBlend": true, "swatch": 1062531877, "ignoreTexelDensity": false, "normalBlend": false}, {"colorBlend": true, "swatch": 2008159925, "ignoreTexelDensity": false, "normalBlend": false}, {"colorBlend": true, "swatch": 2029379834, "ignoreTexelDensity": false, "normalBlend": false}, {"colorBlend": true, "swatch": 1193919178, "ignoreTexelDensity": false, "normalBlend": false}], "material": 6, "bodyPart": "l_glove_legendary"}, "-788290022": {"layers": [{"colorBlend": true, "swatch": -1251036865, "ignoreTexelDensity": false, "normalBlend": false}, {"colorBlend": true, "swatch": -1251036865, "ignoreTexelDensity": false, "normalBlend": false}, {"colorBlend": true, "swatch": -1867646230, "ignoreTexelDensity": false, "normalBlend": false}, {"colorBlend": true, "swatch": 1062531877, "ignoreTexelDensity": false, "normalBlend": false}, {"colorBlend": true, "swatch": 2008159925, "ignoreTexelDensity": false, "normalBlend": false}, {"colorBlend": true, "swatch": 2029379834, "ignoreTexelDensity": false, "normalBlend": false}, {"colorBlend": true, "swatch": 1193919178, "ignoreTexelDensity": false, "normalBlend": false}], "material": 6, "bodyPart": "r_glove_legendary"}}, "scratchAmount": 0.75}